neg_detect/__init__.py
neg_detect/download_udpipe_model.py
neg_detect/gat_model.py
neg_detect/inference.py
neg_detect/pipeline_utils.py
neg_detect/preprocessing.py
neg_detect/spacy_utils.py
neg_detect/test.py
neg_detect/ud_pipe.py
neg_detect-0.1.6.dist-info/licenses/LICENSE
neg_detect-0.1.6.dist-info/METADATA
neg_detect-0.1.6.dist-info/WHEEL
neg_detect-0.1.6.dist-info/top_level.txt
neg_detect-0.1.6.dist-info/RECORD
