Metadata-Version: 2.4
Name: neg-detect
Version: 0.1.6
Summary: A BERT-based inference module for negation detection (cue, scope) -> planning to add focus and event in the near future
Home-page: https://github.com/LeonHammerla/neg-detect
Author: Leon Hammerla
Author-email: 8i40irjqx@mozmail.com
Classifier: Programming Language :: Python :: 3
Classifier: License :: OSI Approved :: MIT License
Classifier: Operating System :: OS Independent
Requires-Python: >=3.6
License-File: LICENSE
Requires-Dist: torch>=1.0.0
Requires-Dist: transformers>=4.0.0
Requires-Dist: spacy>=3.7.6
Requires-Dist: scikit-learn>=1.5.2
Requires-Dist: ufal.udpipe>=1.3.1.1
Requires-Dist: torch-geometric>=2.6.1
Dynamic: author
Dynamic: author-email
Dynamic: classifier
Dynamic: description
Dynamic: description-content-type
Dynamic: home-page
Dynamic: license-file
Dynamic: requires-dist
Dynamic: requires-python
Dynamic: summary
